pyeunomia-0.1.1.dist-info/METADATA
pyeunomia-0.1.1.dist-info/WHEEL
pyeunomia/__init__.py
pyeunomia/core.py
pyeunomia/data/eunomia.duckdb
pyeunomia-0.1.1.dist-info/RECORD
