Metadata-Version: 2.1
Name: pyeunomia
Version: 0.1.1
Summary: A standard dataset in the OMOP (Observational Medical Outcomes Partnership) Common Data Model (CDM) for testing and demonstration purposes
Keywords: OMOP CDM OHDSI
Author-Email: Miguel-Angel Sicilia <msicilia@gmail.com>
License: MIT
Requires-Python: >=3.10
Requires-Dist: duckdb>=0.10.0
